tmm/Changes.txt
tmm/LICENSE.txt
tmm/README.rst
tmm/__init__.py
tmm/color.py
tmm/examples.ipynb
tmm/examples.py
tmm/manual.pdf
tmm/tests.py
tmm/tmm_core.py
tmm-0.1.9.dist-info/LICENSE.txt
tmm-0.1.9.dist-info/METADATA
tmm-0.1.9.dist-info/WHEEL
tmm-0.1.9.dist-info/top_level.txt
tmm-0.1.9.dist-info/RECORD
