Metadata-Version: 2.1
Name: tmm
Version: 0.1.9
Summary: Simulate light propagation in multilayer thin and/or thick films using the fresnel equations and transfer matrix method.
Author-email: Steven Byrnes <steven.byrnes@gmail.com>
License: MIT
Project-URL: Homepage, http://pypi.python.org/pypi/tmm
Project-URL: Repository, https://github.com/sbyrnes321/tmm
Keywords: optics,fresnel,reflection,absorption,photovoltaics,ellipsometry,transfer matrix method
Classifier: Intended Audience :: Science/Research
Classifier: Topic :: Scientific/Engineering
Classifier: License :: OSI Approved :: MIT License
Classifier: Programming Language :: Python :: 3
Requires-Python: >=3
License-File: LICENSE.txt
